AUTHORS
LICENSE
MANIFEST.in
README.md
setup.cfg
setup.py
webobsclient/__init__.py
webobsclient/auth.py
webobsclient/client.py
webobsclient/decorators.py
webobsclient/exceptions.py
webobsclient/models.py
webobsclient/parser.py
webobsclient/request.py
webobsclient/schemas.py
webobsclient/utils.py
webobsclient/version.py
webobsclient.egg-info/PKG-INFO
webobsclient.egg-info/SOURCES.txt
webobsclient.egg-info/dependency_links.txt
webobsclient.egg-info/not-zip-safe
webobsclient.egg-info/requires.txt
webobsclient.egg-info/top_level.txt
webobsclient/contrib/__init__.py
webobsclient/contrib/bpptkg/__init__.py
webobsclient/contrib/bpptkg/singleton.py
webobsclient/contrib/bpptkg/db/__init__.py
webobsclient/contrib/bpptkg/db/query.py
webobsclient/contrib/bpptkg/db/seismic_bulletin.py
webobsclient/contrib/bpptkg/db/sessions.py
webobsclient/contrib/bpptkg/utils/__init__.py
webobsclient/contrib/bpptkg/utils/sqlalchemy.py